yiac/__init__.py
yiac/api.py
yiac/cli.py
yiac-0.1.dev2.dist-info/LICENSE
yiac-0.1.dev2.dist-info/METADATA
yiac-0.1.dev2.dist-info/WHEEL
yiac-0.1.dev2.dist-info/entry_points.txt
yiac-0.1.dev2.dist-info/top_level.txt
yiac-0.1.dev2.dist-info/RECORD
