Metadata-Version: 2.1
Name: yiac
Version: 0.1.dev2
Summary: Xiaomi Yi Python API
Home-page: https://github.com/dr1s/yiac
Author: Daniel Schmitz
License: MIT
Platform: UNKNOWN
